afniRTI/__init__.py
afniRTI/experiment.py
afniRTI/realtime.py
afniRTI/receiver.py
afniRTI-3.0.1.dist-info/LICENSE
afniRTI-3.0.1.dist-info/METADATA
afniRTI-3.0.1.dist-info/WHEEL
afniRTI-3.0.1.dist-info/top_level.txt
afniRTI-3.0.1.dist-info/RECORD
