Metadata-Version: 2.1
Name: afniRTI
Version: 3.0.1
Summary: AFNI Real-Time Interface in Python
Home-page: https://github.com/roopchansinghv/afni-real-time-interface-in-python
Author: V. R-singh
Author-email: for_usenet@yahoo.com
License: UNKNOWN
Platform: UNKNOWN
Classifier: Programming Language :: Python :: 3
Classifier: Operating System :: OS Independent
Requires-Python: >=3.0
